<?xml version="1.0" encoding="UTF-8"?>

<yodaodict>
  <return-phrase><![CDATA[Locke]]></return-phrase>
  
                            <phonetic-symbol>lɔk</phonetic-symbol>
                  <dictcn-speach>Locke</dictcn-speach>
                          <custom-translation>
        <type>ec</type>
                  <translation><content><![CDATA[n. 洛克（姓氏）]]></content></translation>
                </custom-translation>
          
              <yodao-web-dict>
                    <web-translation>
                <key><![CDATA[Locke]]></key>
                          <trans><value><![CDATA[洛克]]></value></trans>
                  <trans><value><![CDATA[乐居镇]]></value></trans>
                  <trans><value><![CDATA[约翰·洛克]]></value></trans>
                </web-translation>
              <web-translation>
                <key><![CDATA[John Locke]]></key>
                          <trans><value><![CDATA[约翰·洛克]]></value></trans>
                  <trans><value><![CDATA[约翰洛克]]></value></trans>
                  <trans><value><![CDATA[约翰]]></value></trans>
                </web-translation>
              <web-translation>
                <key><![CDATA[richard locke]]></key>
                          <trans><value><![CDATA[洛克]]></value></trans>
                </web-translation>
            </yodao-web-dict>
    
          <sexp>0</sexp>
</yodaodict>
